scylla/__init__.py
scylla/__meta__.py
scylla/auth.py
scylla/client.py
scylla/config.py
scylla_client-0.2.1.dist-info/LICENSE
scylla_client-0.2.1.dist-info/WHEEL
scylla_client-0.2.1.dist-info/METADATA
scylla_client-0.2.1.dist-info/RECORD
