Metadata-Version: 2.1
Name: scylla-client
Version: 0.2.1
Summary: Scylla - client for charybdis permission manager
License: MIT
Author: Alexander Lavrov
Author-email: egnod@ya.ru
Requires-Python: >=3.7,<4.0
Classifier: License :: OSI Approved :: MIT License
Classifier: Programming Language :: Python :: 3
Classifier: Programming Language :: Python :: 3.7
Requires-Dist: requests (>=2.22,<3.0)
Requires-Dist: sitri (>=0.4.0,<0.5.0)
